CHANGES.md
LICENSE
docs/README.md
docs/extensions.md
docs/installation.md
docs/quickstart.md
docs/tree.yml
renoir/__init__.py
renoir/__version__.py
renoir/_internal.py
renoir/_shortcuts.py
renoir/apis.py
renoir/cache.py
renoir/constants.py
renoir/debug.py
renoir/errors.py
renoir/extensions.py
renoir/helpers.py
renoir/parsing/__init__.py
renoir/parsing/contents.py
renoir/parsing/lexers.py
renoir/parsing/parsers.py
renoir/parsing/stack.py
renoir/typing.py
renoir/writers.py
renoir-1.7.1.dist-info/LICENSE
renoir-1.7.1.dist-info/METADATA
renoir-1.7.1.dist-info/WHEEL
renoir-1.7.1.dist-info/RECORD
