Metadata-Version: 2.1
Name: renoir
Version: 1.7.1
Summary: A templating engine designed with simplicity in mind
Home-page: https://github.com/emmett-framework/renoir
License: BSD-3-Clause
Keywords: templates,html,web
Author: Giovanni Barillari
Author-email: gi0baro@d4net.org
Requires-Python: >=3.8,<4.0
Classifier: Development Status :: 5 - Production/Stable
Classifier: Environment :: Web Environment
Classifier: Intended Audience :: Developers
Classifier: License :: OSI Approved :: BSD License
Classifier: Operating System :: OS Independent
Classifier: Programming Language :: Python :: 3
Classifier: Programming Language :: Python :: 3.8
Classifier: Programming Language :: Python :: 3.9
Classifier: Programming Language :: Python :: 3.10
Classifier: Programming Language :: Python :: 3.11
Classifier: Programming Language :: Python :: 3.12
Classifier: Topic :: Software Development :: Libraries :: Python Modules
Classifier: Topic :: Text Processing :: Markup :: HTML
Project-URL: Issue Tracker, https://github.com/emmett-framework/renoir/issues
Project-URL: Repository, https://github.com/emmett-framework/renoir
